{
  "name": "龍槍長矛 Dragonlance",
  "type": "weapon",
  "img": "icons/weapons/polearms/glaive-hooked-steel.webp",
  "system": {
    "description": {
      "value": "<p><em>（需同調）</em></p><p>龍槍是一種久負盛名的武器，鑄造它不僅僅需要稀有的金屬，還要有強力的神器加持。在克萊恩，它的誕生源於善神帕拉丁和抗擊龍后邪惡的傳奇英雄們。龍槍分為不同的種類，有步兵使用的長矛款式和騎兵使用的騎槍款式，但其魔法屬性是相同的。</p><p>你用這把魔法武器進行的攻擊檢定和傷害擲骰獲得+3加值。</p><p>當你用這把這把武器擊中一條龍Dragon時，這條龍會受到額外[[/r 3d6]]力場傷害，並且你30尺內由你選擇的任何你能看見的龍可以立刻使用它的反應進行一次近戰攻擊。</p><p></p>",
      "chat": "",
      "unidentified": ""
    },
    "source": "DSotDQ",
    "quantity": 1,
    "weight": 0,
    "price": {
      "value": 0,
      "denomination": "gp"
    },
    "attunement": 1,
    "equipped": false,
    "rarity": "legendary",
    "identified": true,
    "activation": {
      "type": "action",
      "cost": 1,
      "condition": ""
    },
    "duration": {
      "value": "",
      "units": ""
    },
    "cover": null,
    "crewed": false,
    "target": {
      "value": null,
      "width": null,
      "units": "",
      "type": ""
    },
    "range": {
      "value": 10,
      "long": null,
      "units": "ft"
    },
    "uses": {
      "value": null,
      "max": "",
      "per": null,
      "recovery": ""
    },
    "consume": {
      "type": "",
      "target": null,
      "amount": null
    },
    "ability": "",
    "actionType": "mwak",
    "attackBonus": "+3",
    "chatFlavor": "",
    "critical": {
      "threshold": null,
      "damage": ""
    },
    "damage": {
      "parts": [
        [
          "1d10 + @mod +3",
          "piercing"
        ]
      ],
      "versatile": ""
    },
    "formula": "3d6",
    "save": {
      "ability": "",
      "dc": null,
      "scaling": "spell"
    },
    "armor": {
      "value": null
    },
    "hp": {
      "value": null,
      "max": null,
      "dt": null,
      "conditions": ""
    },
    "weaponType": "martialM",
    "baseItem": "pike",
    "properties": {
      "rch": true,
      "amm": false,
      "ver": false,
      "ret": false,
      "ada": false,
      "fin": false,
      "mgc": true,
      "fir": false,
      "lgt": false,
      "two": true,
      "spc": false,
      "thr": false,
      "sil": false,
      "rel": false,
      "hvy": true,
      "foc": false,
      "lod": false
    },
    "proficient": true
  },
  "effects": [],
  "flags": {},
  "_stats": {
    "systemId": "dnd5e",
    "systemVersion": "2.2.1",
    "coreVersion": "12.324",
    "createdTime": 1686486268110,
    "modifiedTime": 1686487743535,
    "lastModifiedBy": "Jo05tXxu7yf2dQe3",
    "compendiumSource": null,
    "duplicateSource": null
  },
  "folder": "0e5TyHz0lyj1wyiB",
  "_id": "ioBHbBcfDcm7JQva",
  "sort": 0,
  "ownership": {
    "default": 0,
    "Jo05tXxu7yf2dQe3": 3
  },
  "_key": "!items!ioBHbBcfDcm7JQva"
}
