{
  "_id": "y13naXoQcHWud3un",
  "name": "克羅諾權杖 Korolnor Scepter",
  "type": "weapon",
  "img": "icons/weapons/staves/staff-blue-jewel.webp",
  "effects": [],
  "folder": null,
  "sort": 0,
  "flags": {},
  "_stats": {
    "coreVersion": "12.324",
    "systemId": null,
    "systemVersion": null,
    "createdTime": null,
    "modifiedTime": null,
    "lastModifiedBy": null,
    "compendiumSource": null,
    "duplicateSource": null
  },
  "ownership": {
    "default": 0
  },
  "system": {
    "description": {
      "value": "<blockquote>\n<h4><strong>沙納塔統治權杖 Rulinc Scepters of Shanatar</strong></h4>\n<p>克羅諾權杖與另外九個沙納塔統治權杖配套。這些權杖分別是:</p>\n<ul>\n<li>阿拉托林權杖Alatorin Scepter（位置不詳）</li>\n<li>巴拉庫爾權杖Barakuir Scepter （由灰矮人王峰下的歐羅恩·瑞道戈Olorn Ridaugaur of Underspires所持有）</li>\n<li>德拉卡洛權杖Drakkalor Scepter （在一條上古紅龍查爾維坎納托Charvekannathor的收藏中）</li>\n<li>至高沙納塔權杖High Shanatar Scepter（位於耐蘭瑟群島）</li>\n<li>伊卡扎權杖Iltkazar Scepter（隱藏在墜星海）</li>\n<li>頌達爾權杖Sondarr Scepter（位置不詳）</li>\n<li>托格羅權杖Torglor Scepter（由哈魯阿的萊瑟爾薩 Ryscelsar貴族家族持有）</li>\n<li>烏托薩姆林權杖Ultoksamrin Scepter（遺失在大冰河Great Glacier附近的迷斯·昂達斯Myth Ondath廢墟中）</li>\n<li>索薩林權杖Xothaerin Scepter （位置不詳）。</li>\n</ul>\n</blockquote>\n<p><em>奇物（需同調）</em></p>\n<p>克羅諾權杖Korolnor Scepter是由矮人眾神鍛造並贈與古代矮人帝國的統治家族的的十根沙納塔統治權杖之一。克羅諾權杖Korolnor Scepter位於何方原本一直無人所知，直到風暴巨人皇后內黎在無痕海海底的一艘沉船上發現它。所有這些統治權杖的大小和形狀都大致相同，但它們的材料和特性不同。</p>\n<p>克羅諾權杖Korolnor Scepter是一根錐形的秘銀權杖，粗和長都如同一條矮人的前臂，底部有一個小小的鉑制把手，頂部有一個圓盤，圓盤上面裝飾著一道由七顆藍色小寶石組成的圓環。</p>\n<p>此權杖可以作為一根魔法短棒使用，你使用此權杖做出的攻擊骰和傷害骰獲得+3加值。</p>\n<p>你可以使用權杖本身的特性，也可以使用龍顱王座Wyrmskull Throne的特性。權杖有10發充能，並在黎明時恢復[[/r 1d6+4]]發充能。權杖的特性如下：</p>\n<ul>\n<li>如果你在地下或水下，你可以使用一個動作，消耗1發充能來確定你到地表或水面的距離。</li>\n<li>以一個動作，你可以花費2發充能，使用權杖施放一個@UUID[Compendium.dnd5e_classpack.new-icon.kRO1zjPXuOLm4qUU]{短訊術 Sending}法術。</li>\n<li>以一個行動，你可以花費3發充能，使用權杖施放一個@UUID[Compendium.dnd5e_classpack.new-icon.7wAk7D98B8gAgKzX]{傳送術 Teleport}法術。如果目的地位於龍顱王座Wyrmskull Throne的60尺內，則不會發生傳送錯誤或發生事故。</li>\n</ul>",
      "chat": "",
      "unidentified": ""
    },
    "source": "SKT",
    "quantity": 1,
    "weight": 0,
    "price": 0,
    "attunement": 0,
    "equipped": false,
    "rarity": "legendary",
    "identified": true,
    "activation": {
      "type": "action",
      "cost": 1,
      "condition": ""
    },
    "duration": {
      "value": null,
      "units": ""
    },
    "target": {
      "value": null,
      "width": null,
      "units": "",
      "type": ""
    },
    "range": {
      "value": 5,
      "long": null,
      "units": "ft"
    },
    "uses": {
      "value": 10,
      "max": "10",
      "per": "charges"
    },
    "consume": {
      "type": "",
      "target": "",
      "amount": null
    },
    "ability": "",
    "actionType": "mwak",
    "attackBonus": "3",
    "chatFlavor": "",
    "critical": {
      "threshold": null,
      "damage": ""
    },
    "damage": {
      "parts": [
        [
          "1d4 + @mod +3",
          "bludgeoning"
        ]
      ],
      "versatile": ""
    },
    "formula": "1d6+4",
    "save": {
      "ability": "",
      "dc": null,
      "scaling": "spell"
    },
    "armor": {
      "value": 10
    },
    "hp": {
      "value": 0,
      "max": 0,
      "dt": null,
      "conditions": ""
    },
    "weaponType": "simpleM",
    "baseItem": "club",
    "properties": {
      "rch": false,
      "amm": false,
      "ver": false,
      "ret": false,
      "fir": false,
      "ada": false,
      "fin": false,
      "mgc": true,
      "lgt": true,
      "two": false,
      "spc": false,
      "thr": false,
      "sil": false,
      "hvy": false,
      "rel": false,
      "foc": false,
      "lod": false
    },
    "proficient": false
  },
  "_key": "!items!y13naXoQcHWud3un"
}
