{
  "_id": "lyMVOEI1JrCaqVwz",
  "name": "鑲有月長石moonstones的銀酒杯chalice",
  "type": "loot",
  "img": "icons/containers/kitchenware/goblet-jeweled-blue-grey.webp",
  "effects": [],
  "folder": null,
  "sort": 0,
  "flags": {},
  "_stats": {
    "coreVersion": "12.324",
    "systemId": null,
    "systemVersion": null,
    "createdTime": null,
    "modifiedTime": null,
    "lastModifiedBy": null,
    "compendiumSource": null,
    "duplicateSource": null
  },
  "ownership": {
    "default": 0
  },
  "system": {
    "description": {
      "value": "這是一種換金道具。",
      "chat": "",
      "unidentified": ""
    },
    "source": "DMG",
    "quantity": 1,
    "weight": 0,
    "price": 750,
    "attunement": 0,
    "equipped": false,
    "rarity": "",
    "identified": true
  },
  "_key": "!items!lyMVOEI1JrCaqVwz"
}
