{
  "_id": "5GWYJBfc1aZ6415M",
  "name": "目盲/耳聾術 Blindness/Deafness",
  "type": "spell",
  "flags": {
    "midiProperties": {
      "confirmTargets": "always",
      "autoFailFriendly": false,
      "autoSaveFriendly": false,
      "critOther": false,
      "offHandWeapon": false,
      "magicdam": false,
      "magiceffect": false,
      "concentration": false,
      "noConcentrationCheck": false,
      "toggleEffect": false,
      "ignoreTotalCover": false
    },
    "midi-qol": {
      "rollAttackPerTarget": "always",
      "itemCondition": "",
      "effectCondition": ""
    }
  },
  "img": "modules/dnd5e_classpack/Nicons/Ability_Hibernation.png",
  "effects": [
    {
      "changes": [
        {
          "key": "flags.midi-qol.disadvantage.attack.all",
          "mode": 0,
          "value": "1",
          "priority": null
        },
        {
          "key": "flags.midi-qol.grants.advantage.attack.all",
          "mode": 0,
          "value": "1",
          "priority": null
        }
      ],
      "description": "- A blinded creature can't see and automatically fails any ability check that requires sight.<br />- Attack rolls against the creature have advantage, and the creature's attack rolls have disadvantage.",
      "disabled": false,
      "duration": {
        "rounds": null,
        "seconds": null,
        "turns": null,
        "startTime": null,
        "combat": null,
        "startRound": null,
        "startTurn": null
      },
      "flags": {
        "dfreds-convenient-effects": {
          "isConvenient": true,
          "isDynamic": false,
          "isViewable": true,
          "nestedEffects": [],
          "subEffects": []
        }
      },
      "name": "Blinded",
      "origin": "Compendium.dnd5e_classpack.new-icon.Item.5GWYJBfc1aZ6415M",
      "tint": "#ffffff",
      "transfer": false,
      "statuses": [
        "Convenient Effect: Blinded",
        "blinded"
      ],
      "_id": "7lKV7PMgMj9lYGr9",
      "_stats": {
        "coreVersion": "12.324",
        "systemId": null,
        "systemVersion": null,
        "createdTime": null,
        "modifiedTime": null,
        "lastModifiedBy": null,
        "compendiumSource": null,
        "duplicateSource": null
      },
      "img": "modules/dfreds-convenient-effects/images/blinded.svg",
      "type": "base",
      "system": {},
      "sort": 0,
      "_key": "!items.effects!5GWYJBfc1aZ6415M.7lKV7PMgMj9lYGr9"
    },
    {
      "changes": [],
      "description": "- A deafened creature can't hear and automatically fails any ability check that requires hearing.",
      "disabled": false,
      "duration": {
        "rounds": null,
        "seconds": null,
        "turns": null,
        "startTime": null,
        "combat": null,
        "startRound": null,
        "startTurn": null
      },
      "flags": {
        "dfreds-convenient-effects": {
          "isConvenient": true,
          "isDynamic": false,
          "isViewable": true,
          "nestedEffects": [],
          "subEffects": []
        }
      },
      "name": "Deafened",
      "origin": "Compendium.dnd5e_classpack.new-icon.Item.5GWYJBfc1aZ6415M",
      "tint": "#ffffff",
      "transfer": false,
      "statuses": [
        "Convenient Effect: Deafened",
        "deafened"
      ],
      "_id": "5rljVKiE7mq3gbsN",
      "_stats": {
        "coreVersion": "12.324",
        "systemId": null,
        "systemVersion": null,
        "createdTime": null,
        "modifiedTime": null,
        "lastModifiedBy": null,
        "compendiumSource": null,
        "duplicateSource": null
      },
      "img": "modules/dfreds-convenient-effects/images/deafened.svg",
      "type": "base",
      "system": {},
      "sort": 0,
      "_key": "!items.effects!5GWYJBfc1aZ6415M.5rljVKiE7mq3gbsN"
    }
  ],
  "system": {
    "description": {
      "value": "<div class=\"description \"> 你嘗試令敵人目盲或耳聾。在施法距離內指定一個你能看見的生物，並迫使其進行一次體質豁免。豁免失敗者將在法術持續時間內陷入目盲或耳聾（由你選擇）。目標可以在每次自己回合結束時再進行一次體質豁免，豁免成功則法術終止。\n<br><strong>升環施法效應。</strong>使用3環或更高法術位施展該法術時，你使用的法術位每比2環高一環，就可以多指定一個目標。\n<br></div>",
      "chat": "",
      "unidentified": ""
    },
    "source": "PHB pg. 219",
    "activation": {
      "type": "action",
      "cost": 1,
      "condition": ""
    },
    "duration": {
      "value": 1,
      "units": "minute"
    },
    "target": {
      "value": 1,
      "units": "",
      "type": "creature"
    },
    "range": {
      "value": 30,
      "long": 0,
      "units": "ft"
    },
    "uses": {
      "value": 0,
      "max": 0,
      "per": ""
    },
    "consume": {
      "type": "",
      "target": "",
      "amount": null
    },
    "ability": "",
    "actionType": "save",
    "attackBonus": 0,
    "chatFlavor": "",
    "critical": null,
    "damage": {
      "parts": [],
      "versatile": "",
      "value": ""
    },
    "formula": "",
    "save": {
      "ability": "con",
      "dc": null,
      "scaling": "spell"
    },
    "level": 2,
    "school": "nec",
    "components": {
      "value": "",
      "vocal": true,
      "somatic": false,
      "material": false,
      "ritual": false,
      "concentration": false
    },
    "materials": {
      "value": "",
      "consumed": false,
      "cost": 0,
      "supply": 0
    },
    "preparation": {
      "mode": "prepared",
      "prepared": false
    },
    "scaling": {
      "mode": "level",
      "formula": ""
    },
    "properties": [
      "vocal",
      "mgc"
    ]
  },
  "ownership": {
    "default": 0
  },
  "folder": null,
  "sort": 3900000,
  "_stats": {
    "systemId": "dnd5e",
    "systemVersion": "3.1.1",
    "coreVersion": "12.324",
    "createdTime": 1711702894742,
    "modifiedTime": 1711702896184,
    "lastModifiedBy": "BKSGjEZVDtK4HB0J",
    "compendiumSource": null,
    "duplicateSource": null
  },
  "_key": "!items!5GWYJBfc1aZ6415M"
}
