{
  "name": "光耀禱詞Word of Radiance",
  "type": "spell",
  "flags": {
    "midiProperties": {
      "confirmTargets": "always",
      "saveDamage": "nodam",
      "bonusSaveDamage": "fulldam",
      "autoFailFriendly": false,
      "autoSaveFriendly": false,
      "critOther": false,
      "offHandWeapon": false,
      "magicdam": true,
      "magiceffect": false,
      "concentration": false,
      "noConcentrationCheck": false,
      "toggleEffect": false,
      "ignoreTotalCover": false
    },
    "midi-qol": {
      "rollAttackPerTarget": "always",
      "removeAttackDamageButtons": "default",
      "itemCondition": "",
      "effectCondition": "",
      "AoETargetType": "enemy",
      "AoETargetTypeIncludeSelf": false,
      "autoTarget": "default"
    }
  },
  "img": "icons/magic/light/explosion-star-glow-blue-purple.webp",
  "_id": "EoHUtMRA7ftylPNt",
  "effects": [],
  "system": {
    "description": {
      "value": "<p>你念出神聖的詞語，灼熱的光輝隨之噴薄而出。每個你選擇的、處於你周圍5英尺內、你能看見的生物必須通過一次體質豁免檢定，否則受到1d6點光耀傷害。<br />此法術的傷害在你達到5級（2d6），11級（3d6），和17級（4d6）時提高1d6點</p>",
      "chat": "",
      "unidentified": ""
    },
    "source": "XGE",
    "activation": {
      "type": "action",
      "cost": 1,
      "condition": ""
    },
    "duration": {
      "value": "1",
      "units": ""
    },
    "target": {
      "value": 6,
      "units": "ft",
      "type": "radius"
    },
    "range": {
      "value": null,
      "long": null,
      "units": "self"
    },
    "uses": {
      "value": 0,
      "max": 0,
      "per": ""
    },
    "consume": {
      "type": "",
      "target": null,
      "amount": null
    },
    "ability": "",
    "actionType": "save",
    "attackBonus": 0,
    "chatFlavor": "",
    "critical": null,
    "damage": {
      "parts": [
        [
          "1d6",
          "radiant"
        ]
      ],
      "versatile": ""
    },
    "formula": "",
    "save": {
      "ability": "con",
      "dc": null,
      "scaling": "spell"
    },
    "level": 0,
    "school": "evo",
    "components": {
      "value": "",
      "vocal": true,
      "somatic": false,
      "material": true,
      "ritual": false,
      "concentration": false
    },
    "materials": {
      "value": "一塊聖徽",
      "consumed": false,
      "cost": 0,
      "supply": 0
    },
    "preparation": {
      "mode": "prepared",
      "prepared": false
    },
    "scaling": {
      "mode": "cantrip",
      "formula": "1d6"
    },
    "properties": [
      "vocal",
      "material",
      "mgc"
    ]
  },
  "ownership": {
    "default": 0
  },
  "folder": null,
  "sort": 11500000,
  "_stats": {
    "systemId": "dnd5e",
    "systemVersion": "3.2.0",
    "coreVersion": "12.327",
    "createdTime": null,
    "modifiedTime": 1719581117793,
    "lastModifiedBy": "Yu3wahtyxZLxHbwo",
    "compendiumSource": null,
    "duplicateSource": null
  },
  "_key": "!items!EoHUtMRA7ftylPNt"
}
