{
  "name": "高等術法會大法師 Mage of High Sorcery",
  "type": "background",
  "img": "icons/environment/settlement/city-night-spire.webp",
  "system": {
    "description": {
      "value": "<p>高等術法會是一個由施法者構成的組織，其成員致力於研習魔法和防止魔法被濫用，你使用魔法的天賦引起了該組織的關注。高等術法會對你進行了訓練，但你是否能直面危險的試煉、正式成為該組織的一員，依然是件懸而未決的事情。高等術法會分為三個法師會：仁慈善良的白袍法師會、維護平衡的紅袍法師會以及冷酷無情的黑袍法師會，你研習魔法的熱情已指引你傾向認同某個法師會的理念。</p><p>在克萊恩世界，許多人認為高等術法會的成員只有法師，但實際上該組織也接受法師以外的成員，比如術士、邪術師和其他施法者。</p><hr /><p><strong>技能熟練項</strong>：奧秘，歷史<br /><strong>語言</strong>：任選兩門語言<br /><strong>裝備</strong>：一瓶@UUID[Compendium.dnd5e_classpack.itempack.Item.1B08608A7AF77C85]{有色墨水}，一支@UUID[Compendium.dnd5e_classpack.itempack.Item.A32E3C5845F5A20C]{墨水筆}，一套@UUID[Compendium.dnd5e_classpack.itempack.Item.10F92CBBA91150E7]{普通衣物}，以及一個裝有 10gp 的@UUID[Compendium.dnd5e_classpack.itempack.Item.2C22C4FE00679D76]{腰包}<br /><strong>特性</strong>：你獲得@UUID[Compendium.dnd5e_classpack.feats-all.Item.kvuCAI5XQOXNQNzg]{高等術法入門}專長。此外，在高等術法會還擁有的大法師塔里，該組織可以無限期地為你免費提供儉樸的食宿，你也可以在某位組織成員的家中借住一晚。</p><hr /><h4><strong>建立高等術法會大法師Building a Mage of High Sorcery Character</strong></h4><p>高等術法會成員通常是@UUID[Compendium.dnd5e_classpack.classes-new.Item.dLA1lQ2nRUUWFwZU]{術士}，@UUID[Compendium.dnd5e_classpack.classes-new.Item.1bisexH4xwv2Mz5T]{邪術師}或@UUID[Compendium.dnd5e_classpack.classes-new.Item.nPAjnlZywUaKTfol]{法師}，無論子職。但傳統施法者們並不太歡迎通過奉獻獲得魔法的施法者。儘管如此，高等術法會還是很精明的，他們很少放任獨特的機會或個體白白溜走。若是使用武藝的職業習得了魔法，也有可能在三個法師會中獲得罕見的一席之地。</p><hr /><h4><strong>高等術法會大法師飾品Mage of High Sorcery Trinkets</strong></h4><p>當你建立角色時，根據高等術法會大法師飾品表（而非玩家手冊的飾品表）骰出一個初始飾品。</p><table><caption><strong>高等術法會飾品表 Mage of High Sorcery Trinkets</strong></caption><thead><tr><th><p>[[/r d6]]</p></th><th><p>飾品</p></th></tr></thead><tbody><tr><td><p>1</p></td><td><p>一封未拆的信，來自你第一個老師</p></td></tr><tr><td><p>2</p></td><td><p>一根斷裂的魔杖，由黑色、紅色或白色的木頭製成</p></td></tr><tr><td><p>3</p></td><td><p>一個卷軸，印有難以理解的公式</p></td></tr><tr><td><p>4</p></td><td><p>一個沒什麼具體用處的裝置，覆蓋著彩色的石頭，可以被折成各種奇特的形狀</p></td></tr><tr><td><p>5</p></td><td><p>一個腰包或者一本法術書，印有高等術法會的三月標誌</p></td></tr><tr><td><p>6</p></td><td><p>一個透鏡，可以讓你看見克萊恩的隱形黑月努塔瑞</p></td></tr></tbody></table><hr /><blockquote><h3>額外專長Bonus Feats</h3><p>無論你為一個龍槍戰役中的角色選擇哪個背景，你都會獲得如下文詳述的額外專長bonus feats。被捲入長槍戰爭或克萊恩上其他衝突的角色會因為他們所面臨的劇變而改變。</p><h4>一級額外專長1st-Level Bonus Feat</h4><p>如果你的背景選擇了索蘭尼亞騎士或高等術法會大法師，你將獲得該背景中的專長。如果你選擇的背景不提供專長，你獲得以下額外專長中的一個。</p><ul><li><p>@UUID[Compendium.dnd5e_classpack.feats-all.Item.sYRjltuR7nYyIMOg]{熟習Skilled}</p></li><li><p>@UUID[Compendium.dnd5e_classpack.feats-all.Item.1qPQNtq5EQwEa7OC]{健壯Tough }</p></li></ul><h4>四級額外專長4th-Level Bonus Feat</h4><p>在四級時，你可以從上面的一級專長中或下列專長中再選擇一個額外專長。</p><ul><li><p>@UUID[Compendium.dnd5e_classpack.feats-all.Item.F61VHliXuJZCQVE8]{黑袍入道 Adept of the Black Robes}</p></li><li><p>@UUID[Compendium.dnd5e_classpack.feats-all.Item.CDe5J93lIQwgwLKv]{紅袍入道 Adept of the Red Robes}</p></li><li><p>@UUID[Compendium.dnd5e_classpack.feats-all.Item.WEoKNO09o7l1o2fU]{白袍入道 Adept of the White Robes}</p></li><li><p>@UUID[Compendium.dnd5e_classpack.feats-all.Item.ZSjxby9CMumX5Fex]{警覺 Alert }</p></li><li><p>@UUID[Compendium.dnd5e_classpack.feats-all.Item.v7FupE4PAUZm4cZP]{神恩眷顧 Divinely Favored}</p></li><li><p>@UUID[Compendium.dnd5e_classpack.feats-all.Item.3S1gwW448LAjav0D]{皇冠騎士 Knight of the Crown}</p></li><li><p>@UUID[Compendium.dnd5e_classpack.feats-all.Item.HHd0zVjbgfh1os86]{玫瑰騎士 Knight of the Rose}</p></li><li><p>@UUID[Compendium.dnd5e_classpack.feats-all.Item.YDV2oBAXqkJVp6qX]{聖劍騎士 Knight of the Sword}</p></li><li><p>@UUID[Compendium.dnd5e_classpack.feats-all.Item.yGfRarTvGYK2vxih]{靈活移動 Mobile}</p></li><li><p>@UUID[Compendium.dnd5e_classpack.feats-all.Item.Mxcc5Omx0ixFGeyH]{哨兵 Sentinel}</p></li><li><p>@UUID[Compendium.dnd5e_classpack.feats-all.Item.80vytZPJ9jOtZRPX]{戰地施法者 War Caster}</p></li></ul><p>無論你選擇了哪個背景，包括@UUID[Compendium.dnd5e_classpack.BackgroundList.Item.FYFPB20vvtDQUcYR]{索蘭尼亞騎士}和@UUID[Compendium.dnd5e_classpack.BackgroundList.Item.f1YSso6o1t0l4xoI]{高等術法會大法師}，你都會在四級時獲得如上文所列出的額外專長。如果你選擇的專長有任何先決條件，你必須滿足所有的先決條件。</p></blockquote>",
      "chat": "",
      "unidentified": ""
    },
    "source": "DSotDQ",
    "advancement": [
      {
        "_id": "8vzl1zqmGsVbeeZY",
        "type": "ItemChoice",
        "configuration": {
          "choices": {
            "4": 1
          },
          "allowDrops": true,
          "type": "feat",
          "pool": [
            "Compendium.dnd5e_classpack.feats-all.Item.sYRjltuR7nYyIMOg",
            "Compendium.dnd5e_classpack.feats-all.Item.1qPQNtq5EQwEa7OC",
            "Compendium.dnd5e_classpack.feats-all.Item.F61VHliXuJZCQVE8",
            "Compendium.dnd5e_classpack.feats-all.Item.CDe5J93lIQwgwLKv",
            "Compendium.dnd5e_classpack.feats-all.Item.WEoKNO09o7l1o2fU",
            "Compendium.dnd5e_classpack.feats-all.Item.ZSjxby9CMumX5Fex",
            "Compendium.dnd5e_classpack.feats-all.Item.v7FupE4PAUZm4cZP",
            "Compendium.dnd5e_classpack.feats-all.Item.yGfRarTvGYK2vxih",
            "Compendium.dnd5e_classpack.feats-all.Item.Mxcc5Omx0ixFGeyH",
            "Compendium.dnd5e_classpack.feats-all.Item.80vytZPJ9jOtZRPX"
          ],
          "spell": null,
          "restriction": {
            "type": "feat"
          },
          "hint": "論你為一個龍槍戰役中的角色選擇哪個背景，你都會獲得如下文詳述的額外專長bonus feats。被捲入長槍戰爭或克萊恩上其他衝突的角色會因為他們所面臨的劇變而改變。"
        },
        "value": {},
        "title": "獲得四級專長"
      },
      {
        "_id": "XpEwN2cYZPreHCFv",
        "type": "ItemGrant",
        "configuration": {
          "items": [
            "Compendium.dnd5e_classpack.feats-all.Item.kvuCAI5XQOXNQNzg"
          ],
          "optional": false,
          "spell": null
        },
        "value": {},
        "level": 1,
        "title": "獲得背景專長"
      }
    ]
  },
  "effects": [],
  "flags": {},
  "_stats": {
    "systemId": "dnd5e",
    "systemVersion": "2.2.1",
    "coreVersion": "12.324",
    "createdTime": 1686481605404,
    "modifiedTime": 1686482165327,
    "lastModifiedBy": "Jo05tXxu7yf2dQe3",
    "compendiumSource": null,
    "duplicateSource": null
  },
  "folder": "gG7DRov79dW7hHdo",
  "_id": "f1YSso6o1t0l4xoI",
  "sort": 0,
  "ownership": {
    "default": 0,
    "Jo05tXxu7yf2dQe3": 3
  },
  "_key": "!items!f1YSso6o1t0l4xoI"
}
