{
  "_id": "0nEK2U1jS5PETo02",
  "name": "大地結社 Circle of the Land",
  "type": "subclass",
  "img": "modules/dnd5e_classpack/Nicons/Achievement_Zone_TownlongSteppes.png",
  "effects": [],
  "folder": null,
  "sort": 0,
  "flags": {},
  "system": {
    "description": {
      "value": "<p>        創立大地結社的秘術師和智者們守護著遠古的知識與各種傳統儀式。結社的德魯伊們聚集在神樹之環下或石陣之中，他們用德魯伊語低聲交流，傳遞著原初的秘密。結社中最睿智的成員地位尊貴，他們如教團的首席祭司一樣維護著上古誓約，併爲其領導下的眾人傳道解惑。作為結社的一員，大地結社的儀式與你建立起神秘的連線，使你的魔力受到大地的影響。</p>\n<p><strong>附贈戲法Bonus Cantrip</strong></p>\n<p>        在第2級選擇該結社時，你學會一個額外的德魯伊戲法。</p>",
      "chat": "",
      "unidentified": ""
    },
    "source": "PHB pg. 79",
    "identifier": "circle-of-the-land",
    "classIdentifier": "druid",
    "advancement": [
      {
        "_id": "hsajb6n5oahnputt",
        "type": "ItemGrant",
        "configuration": {
          "items": [
            "Compendium.dnd5e_classpack.class-abilityphb.KCU5siz0zvI8Evwu"
          ],
          "optional": false,
          "spell": null
        },
        "value": {},
        "level": 2,
        "title": "職業特性"
      },
      {
        "_id": "18n4ff654jbha0pe",
        "type": "ItemGrant",
        "configuration": {
          "items": [
            "Compendium.dnd5e_classpack.class-abilityphb.jQTXDqRdk7L4u3fy"
          ],
          "optional": false,
          "spell": null
        },
        "value": {},
        "level": 3,
        "title": "職業特性"
      },
      {
        "_id": "xpakmn74xcpf4lhs",
        "type": "ItemGrant",
        "configuration": {
          "items": [
            "Compendium.dnd5e_classpack.class-abilityphb.SVVsJmrNTV8gskhi"
          ],
          "optional": false,
          "spell": null
        },
        "value": {},
        "level": 6,
        "title": "職業特性"
      },
      {
        "_id": "0v93r7wvzu1jq6ld",
        "type": "ItemGrant",
        "configuration": {
          "items": [
            "Compendium.dnd5e_classpack.class-abilityphb.aIXN1FpSuEH3Midz"
          ],
          "optional": false,
          "spell": null
        },
        "value": {},
        "level": 10,
        "title": "職業特性"
      },
      {
        "_id": "i5r6gk99r58e7ux9",
        "type": "ItemGrant",
        "configuration": {
          "items": [
            "Compendium.dnd5e_classpack.class-abilityphb.S42pVI3gy08lxwI4"
          ],
          "optional": false,
          "spell": null
        },
        "value": {},
        "level": 14,
        "title": "職業特性"
      },
      {
        "_id": "13xi8i08h0egq7k7",
        "type": "ScaleValue",
        "configuration": {
          "identifier": "jieshe",
          "type": "string",
          "distance": {
            "units": ""
          },
          "scale": {
            "3": {
              "value": "獲得 3rd 結社法術"
            },
            "5": {
              "value": "獲得 5th 結社法術"
            },
            "7": {
              "value": "獲得 7th 結社法術"
            },
            "9": {
              "value": "獲得 9th 結社法術"
            }
          }
        },
        "value": {},
        "title": "結社法術"
      }
    ],
    "spellcasting": {
      "progression": "none",
      "ability": ""
    }
  },
  "ownership": {
    "default": 0
  },
  "_stats": {
    "systemId": "dnd5e",
    "systemVersion": "2.2.1",
    "coreVersion": "12.324",
    "createdTime": null,
    "modifiedTime": 1685801154688,
    "lastModifiedBy": "Jo05tXxu7yf2dQe3",
    "compendiumSource": null,
    "duplicateSource": null
  },
  "_key": "!items!0nEK2U1jS5PETo02"
}
