{
  "_id": "td4iqgqU7Neeca05",
  "name": "王冠之誓 Oath of The Crown（SCAG）",
  "type": "subclass",
  "img": "modules/dnd5e_classpack/Nicons/INV_Circlet_Firelands_D_01.png",
  "effects": [],
  "folder": null,
  "sort": 0,
  "flags": {},
  "_stats": {
    "coreVersion": "12.324",
    "systemId": null,
    "systemVersion": null,
    "createdTime": null,
    "modifiedTime": null,
    "lastModifiedBy": null,
    "compendiumSource": null,
    "duplicateSource": null
  },
  "ownership": {
    "default": 0
  },
  "system": {
    "description": {
      "value": "<p>王冠之誓，是一種對於文明的崇高理想。它通常體現為一種對民族精神的認同，一種對君王的效忠，或者是一種對於律法和規則的維護。遵循王冠之誓的聖武士們獻身於整個社會，致力使社會整體遵循於法律。他們是秩序社會最後的守護者，時刻提防著混亂和野蠻的浪潮將文明摧毀；一般人們會稱呼他們為守護者，典範或者是哨兵。通常，會立下這個誓言的聖武士是一個效忠於國家或者君王的騎士，並且遵守這個誓言也是他們進入這個社會等級的一部分條件。</p>\n<h3><strong>王冠之信條</strong></h3>\n<p>王冠的信條通常由聖武士們所效忠的對象制定。不過，通常這些信條會強調如下幾項。</p>\n<ul>\n<li><strong>律法：</strong>律法至上。它是文明的基石並且必須被莊重對待。</li>\n<li><strong>忠誠：</strong>言出必行。失去了忠誠，誓言和律法將毫無意義。</li>\n<li><strong>勇氣：</strong>無所畏懼。你必須願意在秩序被動搖時挺身而出，即使勝算渺茫。如果你不行動，那麼誰會？</li>\n<li><strong>責任：</strong>恪盡職守。你必須認識到你行動的重要性併爲之承擔後果，你要盡你最大努力完成你的責任和義務。</li>\n</ul>\n<p><strong>聖誓法術Oath Spells</strong></p>\n<p><em>你獲得以下聖誓法術。</em></p>\n<table border=\"1\">\n<tbody>\n<tr>\n<th>聖騎士等級</th>\n<th>法術</th>\n</tr>\n<tr>\n<td><strong>3rd</strong></td>\n<td>@UUID[Compendium.dnd5e_classpack.new-icon.Ja6HpsLeGA9MQ0Rm]{命令術}@UUID[Compendium.dnd5e_classpack.new-icon.C2KWIIG69H9UWb9e]{強令對決}</td>\n</tr>\n<tr>\n<td><strong>5th</strong></td>\n<td>@UUID[Compendium.dnd5e_classpack.new-icon.DLyjjM6qTHBCSFCx]{守護之鏈}@UUID[Compendium.dnd5e_classpack.new-icon.T4zFq0zTHnzZeO9t]{誠實之域}</td>\n</tr>\n<tr>\n<td><strong>9th</strong></td>\n<td>@UUID[Compendium.dnd5e_classpack.new-icon.XfYgB18GC8OgETjG]{活力靈光}@UUID[Compendium.dnd5e_classpack.new-icon.SrPArp6F9Ixot8Mh]{靈體衛士}</td>\n</tr>\n<tr>\n<td><strong>13th</strong></td>\n<td>@UUID[Compendium.dnd5e_classpack.new-icon.lopw7wVkPoE7gbNu]{放逐術}@UUID[Compendium.dnd5e_classpack.new-icon.LPXdi1HhVx8kJWYy]{信仰守衛}</td>\n</tr>\n<tr>\n<td><strong>17th</strong></td>\n<td>@UUID[Compendium.dnd5e_classpack.new-icon.Y7NbrJlvdfWKm57j]{原力法陣}@UUID[Compendium.dnd5e_classpack.new-icon.QdYv5sEuGwinew7D]{指使術}</td>\n</tr>\n</tbody>\n</table>",
      "chat": "",
      "unidentified": ""
    },
    "source": "SCAG",
    "identifier": "oath-of-the-crown",
    "classIdentifier": "paladin",
    "advancement": [
      {
        "_id": "eatgwz3uuhikhxhp",
        "type": "ItemGrant",
        "configuration": {
          "items": [
            "Compendium.dnd5e_classpack.new-icon.Ja6HpsLeGA9MQ0Rm",
            "Compendium.dnd5e_classpack.new-icon.C2KWIIG69H9UWb9e"
          ],
          "optional": true
        },
        "value": {},
        "level": 3,
        "title": "獲得法術",
        "icon": ""
      },
      {
        "_id": "0nj4up600131mxrz",
        "type": "ItemGrant",
        "configuration": {
          "items": [
            "Compendium.dnd5e_classpack.new-icon.DLyjjM6qTHBCSFCx",
            "Compendium.dnd5e_classpack.new-icon.T4zFq0zTHnzZeO9t"
          ],
          "optional": true
        },
        "value": {},
        "level": 5,
        "title": "獲得法術",
        "icon": ""
      },
      {
        "_id": "o7zsqvhhqe97wpjf",
        "type": "ItemGrant",
        "configuration": {
          "items": [
            "Compendium.dnd5e_classpack.new-icon.XfYgB18GC8OgETjG",
            "Compendium.dnd5e_classpack.new-icon.SrPArp6F9Ixot8Mh"
          ],
          "optional": true
        },
        "value": {},
        "level": 9,
        "title": "獲得法術",
        "icon": ""
      },
      {
        "_id": "p1y9vt6zcebyxva9",
        "type": "ItemGrant",
        "configuration": {
          "items": [
            "Compendium.dnd5e_classpack.new-icon.LPXdi1HhVx8kJWYy",
            "Compendium.dnd5e_classpack.new-icon.lopw7wVkPoE7gbNu"
          ],
          "optional": true
        },
        "value": {},
        "level": 13,
        "title": "獲得法術",
        "icon": ""
      },
      {
        "_id": "f4nvci24wf5uue8v",
        "type": "ItemGrant",
        "configuration": {
          "items": [
            "Compendium.dnd5e_classpack.new-icon.Y7NbrJlvdfWKm57j",
            "Compendium.dnd5e_classpack.new-icon.QdYv5sEuGwinew7D"
          ],
          "optional": true
        },
        "value": {},
        "level": 17,
        "title": "獲得法術",
        "icon": ""
      },
      {
        "_id": "v9tf4ikkfjxv72bq",
        "type": "ItemGrant",
        "configuration": {
          "items": [
            "Compendium.dnd5e_classpack.extra-ability.xOBdlv4Zjgee9YqR",
            "Compendium.dnd5e_classpack.extra-ability.W9HrZ4ShSAcrZmRL"
          ],
          "optional": false
        },
        "value": {},
        "level": 3,
        "title": "職業特性",
        "icon": ""
      },
      {
        "_id": "cqq00nf7ksv6vy0q",
        "type": "ItemGrant",
        "configuration": {
          "items": [
            "Compendium.dnd5e_classpack.extra-ability.bSCZVMQSSZKxYCPP"
          ],
          "optional": false
        },
        "value": {},
        "level": 7,
        "title": "職業特性",
        "icon": ""
      },
      {
        "_id": "hnaiucd217jv6tvd",
        "type": "ItemGrant",
        "configuration": {
          "items": [
            "Compendium.dnd5e_classpack.extra-ability.loa1FeErjePHZ0VG"
          ],
          "optional": false
        },
        "value": {},
        "level": 15,
        "title": "職業特性",
        "icon": ""
      },
      {
        "_id": "1tqlmkmug0xjo9wk",
        "type": "ItemGrant",
        "configuration": {
          "items": [
            "Compendium.dnd5e_classpack.extra-ability.l17hcUnMwg8jKByw"
          ],
          "optional": false
        },
        "value": {},
        "level": 20,
        "title": "職業特性",
        "icon": ""
      }
    ],
    "spellcasting": {
      "progression": "none",
      "ability": ""
    }
  },
  "_key": "!items!td4iqgqU7Neeca05"
}
