{
  "_id": "td4iqgqU7Neeca06",
  "name": "救贖之誓 Oath of Redemption（XGE）",
  "type": "subclass",
  "img": "modules/dnd5e_classpack/Nicons/Spell_Holy_DivineSpirit.png",
  "effects": [],
  "folder": null,
  "sort": 0,
  "flags": {},
  "_stats": {
    "coreVersion": "12.324",
    "systemId": null,
    "systemVersion": null,
    "createdTime": null,
    "modifiedTime": null,
    "lastModifiedBy": null,
    "compendiumSource": null,
    "duplicateSource": null
  },
  "ownership": {
    "default": 0
  },
  "system": {
    "description": {
      "value": "<p>         救贖的誓言為聖武士提供了一條艱難的限制：不到最後關頭就不能動用暴力。獻身於救贖之誓的聖武士相信，任何人都可以得到救贖，仁慈與正義的路應當是所有人都可以走的。這些聖武士直面邪惡的生物，希望使他們棄暗投明，除非是爲了在緊要關頭救人，否則他們絕不會殺死自己的敵人。循此道者，便被稱為救贖者。</p>\n<p>         救贖聖武士雖然可以說是理想主義者，但他們不是傻瓜。他們也明白不死生物、惡魔、魔鬼和其他一些超自然的威脅從本質上就是邪惡的。對於這些堅定不移的邪惡，遵循救贖之誓的聖武士隨時準備用武器和法術來擊垮他們。然而儘管如此，救贖聖武士也在心底祈禱著，總有一天，即使是如此的邪惡也能夠自我救贖。</p>\n<h3><strong>救贖之信條</strong></h3>\n<p>         救贖之誓的信條要求聖武士高標準地保持和平與正義。</p>\n<ul>\n<li><strong>和平：</strong>暴力是最後的手段，交流和理解才是持久和平的正解。</li>\n<li><strong>無辜：</strong>所有人生來都是無辜的，他們走向邪惡往往是環境或某些黑暗力量的影響。通過樹立正確的榜樣，治癒這個殘缺世界的創傷，你可以令任何人走上正確的道路。</li>\n<li><strong>耐心：</strong>改變需要時間。犯下罪行的人必須被誠實與正義時刻提醒。一旦你播下正義的種子，你就必須日復一日地為其努力，直到最終開花結果。</li>\n<li><strong>睿智：</strong>你的心靈必須時刻保持清醒，而你最終也許會被迫承認失敗。既然所有人都可以得到救贖，那麼自然也會有人選擇步入邪惡之巔。你別無選擇，爲了大義只能將其剿滅。任何這樣的行動都應當經過仔細權衡並考慮清楚其後果，但你一旦做出決定，那麼就做到最後。</li>\n</ul>\n<p><strong>聖誓法術Oath Spells</strong></p>\n<p><em>你獲得以下聖誓法術。</em></p>\n<table border=\"1\">\n<tbody>\n<tr>\n<th>聖騎士等級</th>\n<th>法術</th>\n</tr>\n<tr>\n<td><strong>3rd</strong></td>\n<td>@UUID[Compendium.dnd5e_classpack.new-icon.FbxdKcDpSPWuGTLA]{庇護術}@UUID[Compendium.dnd5e_classpack.new-icon.hFHF7vm3FYyTN288]{睡眠術}</td>\n</tr>\n<tr>\n<td><strong>5th</strong></td>\n<td>@UUID[Compendium.dnd5e_classpack.new-icon.6MYwBtZurc8Zw1ac]{安定心神}@UUID[Compendium.dnd5e_classpack.new-icon.syHHJlRPS4rVwCQA]{人類定身術}</td>\n</tr>\n<tr>\n<td><strong>9th</strong></td>\n<td>@UUID[Compendium.dnd5e_classpack.new-icon.895yeeloz2EhpEYC]{法術反制}@UUID[Compendium.dnd5e_classpack.new-icon.BbpCbjCXt14a08Jp]{催眠圖紋}</td>\n</tr>\n<tr>\n<td><strong>13th</strong></td>\n<td>@UUID[Compendium.dnd5e_classpack.new-icon.cdeQPacCcm540OPy]{歐提路克彈力法球}@UUID[Compendium.dnd5e_classpack.new-icon.8xmyW0Ynz0z7Kt3X]{石膚術}</td>\n</tr>\n<tr>\n<td><strong>17th</strong></td>\n<td>@UUID[Compendium.dnd5e_classpack.new-icon.abm5MgV3kejSatZt]{怪物定身術}@UUID[Compendium.dnd5e_classpack.new-icon.31jKHMGJ0vlqdvQU]{力場墻}</td>\n</tr>\n</tbody>\n</table>",
      "chat": "",
      "unidentified": ""
    },
    "source": "XGE",
    "identifier": "oath-of-redemption",
    "classIdentifier": "paladin",
    "advancement": [
      {
        "_id": "eatgwz3uuhikhxhp",
        "type": "ItemGrant",
        "configuration": {
          "items": [
            "Compendium.dnd5e_classpack.new-icon.FbxdKcDpSPWuGTLA",
            "Compendium.dnd5e_classpack.new-icon.hFHF7vm3FYyTN288"
          ],
          "optional": true
        },
        "value": {},
        "level": 3,
        "title": "獲得法術",
        "icon": ""
      },
      {
        "_id": "0nj4up600131mxrz",
        "type": "ItemGrant",
        "configuration": {
          "items": [
            "Compendium.dnd5e_classpack.new-icon.6MYwBtZurc8Zw1ac",
            "Compendium.dnd5e_classpack.new-icon.syHHJlRPS4rVwCQA"
          ],
          "optional": true
        },
        "value": {},
        "level": 5,
        "title": "獲得法術",
        "icon": ""
      },
      {
        "_id": "o7zsqvhhqe97wpjf",
        "type": "ItemGrant",
        "configuration": {
          "items": [
            "Compendium.dnd5e_classpack.new-icon.895yeeloz2EhpEYC",
            "Compendium.dnd5e_classpack.new-icon.BbpCbjCXt14a08Jp"
          ],
          "optional": true
        },
        "value": {},
        "level": 9,
        "title": "獲得法術",
        "icon": ""
      },
      {
        "_id": "p1y9vt6zcebyxva9",
        "type": "ItemGrant",
        "configuration": {
          "items": [
            "Compendium.dnd5e_classpack.new-icon.cdeQPacCcm540OPy",
            "Compendium.dnd5e_classpack.new-icon.8xmyW0Ynz0z7Kt3X"
          ],
          "optional": true
        },
        "value": {},
        "level": 13,
        "title": "獲得法術",
        "icon": ""
      },
      {
        "_id": "f4nvci24wf5uue8v",
        "type": "ItemGrant",
        "configuration": {
          "items": [
            "Compendium.dnd5e_classpack.new-icon.abm5MgV3kejSatZt",
            "Compendium.dnd5e_classpack.new-icon.31jKHMGJ0vlqdvQU"
          ],
          "optional": true
        },
        "value": {},
        "level": 17,
        "title": "獲得法術",
        "icon": ""
      },
      {
        "_id": "v9tf4ikkfjxv72bq",
        "type": "ItemGrant",
        "configuration": {
          "items": [
            "Compendium.dnd5e_classpack.extra-ability.OiCopLiGu5RAozZl",
            "Compendium.dnd5e_classpack.extra-ability.vzqFME5OV7DyzHmy"
          ],
          "optional": false
        },
        "value": {},
        "level": 3,
        "title": "職業特性",
        "icon": ""
      },
      {
        "_id": "cqq00nf7ksv6vy0q",
        "type": "ItemGrant",
        "configuration": {
          "items": [
            "Compendium.dnd5e_classpack.extra-ability.hhdcnaUYZaV2iWIl"
          ],
          "optional": false
        },
        "value": {},
        "level": 7,
        "title": "職業特性",
        "icon": ""
      },
      {
        "_id": "hnaiucd217jv6tvd",
        "type": "ItemGrant",
        "configuration": {
          "items": [
            "Compendium.dnd5e_classpack.extra-ability.aI6Gc7MU4uZ621kr"
          ],
          "optional": false
        },
        "value": {},
        "level": 15,
        "title": "職業特性",
        "icon": ""
      },
      {
        "_id": "1tqlmkmug0xjo9wk",
        "type": "ItemGrant",
        "configuration": {
          "items": [
            "Compendium.dnd5e_classpack.extra-ability.ky0dMTWSMVEztfGF"
          ],
          "optional": false
        },
        "value": {},
        "level": 20,
        "title": "職業特性",
        "icon": ""
      },
      {
        "_id": "7lh1a8vuomo6p7qg",
        "type": "ScaleValue",
        "configuration": {
          "identifier": "huwei",
          "type": "distance",
          "distance": {
            "units": "ft"
          },
          "scale": {
            "7": {
              "value": 10
            },
            "18": {
              "value": 30
            }
          }
        },
        "value": {},
        "title": "護衛光環作用半徑",
        "icon": ""
      }
    ],
    "spellcasting": {
      "progression": "none",
      "ability": ""
    }
  },
  "_key": "!items!td4iqgqU7Neeca06"
}
