{
  "_id": "wQtUjvfS0MXMFp03",
  "name": "預言學派 School of Divination",
  "type": "subclass",
  "img": "modules/dnd5e_classpack/Nicons/Ability_Mage_StudentOfTheMind.png",
  "effects": [],
  "folder": null,
  "sort": 0,
  "flags": {},
  "_stats": {
    "coreVersion": "12.324",
    "systemId": null,
    "systemVersion": null,
    "createdTime": null,
    "modifiedTime": null,
    "lastModifiedBy": null,
    "compendiumSource": null,
    "duplicateSource": null
  },
  "ownership": {
    "default": 0
  },
  "system": {
    "description": {
      "value": "<p>        不管是王侯貴族還是平凡人家，總會想要得到預言師的指點，以尋求對某些過去，現在或未來事情更加明晰的情報。作為一名預言師，你致力於揭開時空與意識的神秘面紗，讓事物看起來更加清楚明瞭。你努力掌握的法術囊括了鑑別、遠視、超自然學識以及預知等各方面內容。</p>\n<p><strong>預言學者Divination Savant</strong></p>\n<p>        從第2級你選擇該學派起，你向法術書中抄寫預言系法術的時間和金錢花費減半。</p>",
      "chat": "",
      "unidentified": ""
    },
    "source": "PHB",
    "identifier": "school-of-divination",
    "classIdentifier": "wizard",
    "advancement": [
      {
        "_id": "u6mkf8avr1c7kg3x",
        "type": "ItemGrant",
        "configuration": {
          "items": [
            "Compendium.dnd5e_classpack.class-abilityphb.JSOUfGgqLBJAj0Dp"
          ],
          "optional": false
        },
        "value": {},
        "level": 2,
        "title": "職業特性",
        "icon": ""
      },
      {
        "_id": "m7xdaseh3xfcxnki",
        "type": "ItemGrant",
        "configuration": {
          "items": [
            "Compendium.dnd5e_classpack.class-abilityphb.grUcT3G8QKVf8H10"
          ],
          "optional": false
        },
        "value": {},
        "level": 6,
        "title": "職業特性",
        "icon": ""
      },
      {
        "_id": "hges9zqopy5eooq6",
        "type": "ItemGrant",
        "configuration": {
          "items": [
            "Compendium.dnd5e_classpack.class-abilityphb.LmVqqh1EO6w4O3FC"
          ],
          "optional": false
        },
        "value": {},
        "level": 10,
        "title": "職業特性",
        "icon": ""
      },
      {
        "_id": "4ji7jkn04mibz987",
        "type": "ItemGrant",
        "configuration": {
          "items": [
            "Compendium.dnd5e_classpack.class-abilityphb.i4N9p6sGcAfNp0b9"
          ],
          "optional": false
        },
        "value": {},
        "level": 14,
        "title": "職業特性",
        "icon": ""
      }
    ],
    "spellcasting": {
      "progression": "none",
      "ability": ""
    }
  },
  "_key": "!items!wQtUjvfS0MXMFp03"
}
