{
  "name": "護甲包裹（自動侏儒）",
  "type": "feat",
  "img": "icons/commodities/tech/frame-copper.webp",
  "system": {
    "description": {
      "value": "<p>你的身體由薄金屬或其他的耐用材料包復著。當你不穿著護甲時，你的基礎護甲等級為13+你的敏捷調整值。</p>",
      "chat": "",
      "unidentified": ""
    },
    "source": "AAG",
    "activation": {
      "type": "",
      "cost": 0,
      "condition": ""
    },
    "duration": {
      "value": null,
      "units": ""
    },
    "cover": null,
    "crewed": false,
    "target": {
      "value": null,
      "width": null,
      "units": "",
      "type": ""
    },
    "range": {
      "value": null,
      "long": null,
      "units": ""
    },
    "uses": {
      "value": null,
      "max": "",
      "per": null,
      "recovery": ""
    },
    "consume": {
      "type": "",
      "target": null,
      "amount": null
    },
    "ability": null,
    "actionType": "",
    "attackBonus": 0,
    "chatFlavor": "",
    "critical": {
      "threshold": null,
      "damage": ""
    },
    "damage": {
      "parts": [],
      "versatile": ""
    },
    "formula": "",
    "save": {
      "ability": "",
      "dc": null,
      "scaling": "spell"
    },
    "type": {
      "value": "race",
      "subtype": ""
    },
    "requirements": "自動侏儒",
    "recharge": {
      "value": null,
      "charged": false
    }
  },
  "effects": [],
  "flags": {},
  "_id": "aGYwjowQOZt9owEd",
  "folder": null,
  "sort": 16000000,
  "ownership": {
    "default": 0
  },
  "_stats": {
    "systemId": "dnd5e",
    "systemVersion": "3.1.1",
    "coreVersion": "12.324",
    "createdTime": null,
    "modifiedTime": 1711712493941,
    "lastModifiedBy": "krICnnplyRFIq4Sm",
    "compendiumSource": null,
    "duplicateSource": null
  },
  "_key": "!items!aGYwjowQOZt9owEd"
}
