{
  "name": "融入清風 (元素裔)",
  "type": "feat",
  "system": {
    "type": {
      "value": "race",
      "subtype": ""
    },
    "description": {
      "value": "<p><strong><span style=\"\"> </span></strong><span style=\"\">你可以通過此特質施展一次 <strong><em>浮空術 levitate</span></em></strong> 且無需任何材料構材。你必須完成一次長休后才能再次啟用該能力。該法術的施法關鍵屬性為體質。</span></p>",
      "chat": "",
      "unidentified": ""
    },
    "source": "EEPC",
    "activation": {
      "type": "",
      "cost": 0,
      "condition": ""
    },
    "duration": {
      "value": null,
      "units": ""
    },
    "target": {
      "value": null,
      "units": "",
      "type": ""
    },
    "range": {
      "value": null,
      "long": null,
      "units": ""
    },
    "uses": {
      "value": 0,
      "max": 0,
      "per": null
    },
    "consume": {
      "type": "",
      "target": null,
      "amount": null
    },
    "ability": null,
    "actionType": "",
    "attackBonus": 0,
    "chatFlavor": "",
    "critical": null,
    "damage": {
      "parts": [],
      "versatile": ""
    },
    "formula": "",
    "save": {
      "ability": "",
      "dc": null,
      "scaling": "spell"
    },
    "requirements": "氣元素裔",
    "recharge": {
      "value": null,
      "charged": false
    }
  },
  "flags": {
    "midiProperties": {
      "confirmTargets": "always",
      "autoFailFriendly": false,
      "autoSaveFriendly": false,
      "critOther": false,
      "offHandWeapon": false,
      "magicdam": false,
      "magiceffect": false,
      "concentration": false,
      "noConcentrationCheck": false,
      "toggleEffect": false,
      "ignoreTotalCover": false
    },
    "midi-qol": {
      "rollAttackPerTarget": "always",
      "itemCondition": "",
      "effectCondition": ""
    }
  },
  "img": "icons/magic/air/air-wave-gust-blue.webp",
  "_id": "AgEKTjVxTl8bytCR",
  "effects": [],
  "ownership": {
    "default": 0
  },
  "folder": null,
  "sort": 4700000,
  "_stats": {
    "systemId": "dnd5e",
    "systemVersion": "3.1.1",
    "coreVersion": "12.324",
    "createdTime": null,
    "modifiedTime": 1712040568807,
    "lastModifiedBy": "krICnnplyRFIq4Sm",
    "compendiumSource": null,
    "duplicateSource": null
  },
  "_key": "!items!AgEKTjVxTl8bytCR"
}
