{
  "_id": "U5Qd4JBsnqhBC4Vv",
  "name": "元素親和",
  "type": "feat",
  "img": "modules/dnd5e_classpack/Nicons/Spell_Nature_ElementalAbsorption.png",
  "system": {
    "type": {
      "value": "class",
      "subtype": ""
    },
    "description": {
      "value": "<p>第6級起，當你施展傷害型別與你@UUID[Compendium.dnd5e_classpack.class-abilityphb.02apnvdAC94ksZIV]{巨龍先祖}相對應的法術時，可以將你的魅力調整值附加到其中一個傷害擲骰上。此時你還可以用1術法點來獲得持續1小時的相應傷害抗性。</p>",
      "chat": "",
      "unidentified": ""
    },
    "source": "PHB pg. 102",
    "activation": {
      "type": "special",
      "cost": null,
      "condition": "1 sorcery point is also required if the resistance is desired."
    },
    "duration": {
      "value": null,
      "units": ""
    },
    "target": {
      "value": null,
      "width": null,
      "units": "",
      "type": ""
    },
    "range": {
      "value": null,
      "long": null,
      "units": ""
    },
    "uses": {
      "value": 0,
      "max": "0",
      "per": "",
      "type": ""
    },
    "consume": {
      "type": "",
      "target": "",
      "amount": null
    },
    "ability": "cha",
    "actionType": "other",
    "attackBonus": 0,
    "chatFlavor": "",
    "critical": null,
    "damage": {
      "parts": [
        [
          "@mod",
          ""
        ]
      ],
      "versatile": "",
      "value": ""
    },
    "formula": "",
    "save": {
      "ability": "",
      "dc": null,
      "scaling": "spell",
      "value": ""
    },
    "requirements": "龍族血脈等級 6",
    "recharge": {
      "value": null,
      "charged": false
    }
  },
  "effects": [],
  "folder": null,
  "sort": 0,
  "flags": {
    "_sheetTab": "description",
    "entityorder": {
      "order": 76
    }
  },
  "_stats": {
    "coreVersion": "12.324",
    "systemId": null,
    "systemVersion": null,
    "createdTime": null,
    "modifiedTime": null,
    "lastModifiedBy": null,
    "compendiumSource": null,
    "duplicateSource": null
  },
  "ownership": {
    "default": 0
  },
  "_key": "!items!U5Qd4JBsnqhBC4Vv"
}
