{
  "_id": "8uE5wtdhiwvoTzHW",
  "name": "奧術傳承 Arcane Initiate",
  "type": "feat",
  "img": "modules/dnd5e_classpack/Nicons/Spell_Arcane_Arcane04.png",
  "system": {
    "type": {
      "value": "class",
      "subtype": ""
    },
    "description": {
      "value": "<p>從1級起，你得到奧秘技能的熟練，並且你可以從法師法術列表選擇兩個戲法掌握。對於你而言，這些戲法是牧師戲法。<br /></span></p>",
      "chat": "",
      "unidentified": ""
    },
    "source": "SCAG",
    "activation": {
      "type": "",
      "cost": 0,
      "condition": ""
    },
    "duration": {
      "value": null,
      "units": ""
    },
    "target": {
      "value": null,
      "width": null,
      "units": "",
      "type": ""
    },
    "range": {
      "value": null,
      "long": null,
      "units": ""
    },
    "uses": {
      "value": 0,
      "max": 0,
      "per": null
    },
    "consume": {
      "type": "",
      "target": null,
      "amount": null
    },
    "ability": null,
    "actionType": "",
    "attackBonus": 0,
    "chatFlavor": "",
    "critical": null,
    "damage": {
      "parts": [],
      "versatile": ""
    },
    "formula": "",
    "save": {
      "ability": "",
      "dc": null,
      "scaling": "spell"
    },
    "requirements": "奧秘領域等級 1",
    "recharge": {
      "value": null,
      "charged": false
    }
  },
  "effects": [
    {
      "_id": "WwkHPYMuFotAiW0I",
      "changes": [
        {
          "key": "system.skills.arc.value",
          "mode": 4,
          "value": "1",
          "priority": null
        }
      ],
      "disabled": false,
      "duration": {
        "startTime": null,
        "seconds": null,
        "combat": null,
        "rounds": null,
        "turns": null,
        "startRound": null,
        "startTurn": null
      },
      "origin": "Compendium.dnd5e_classpack.extra-ability.8uE5wtdhiwvoTzHW",
      "transfer": true,
      "flags": {},
      "tint": "#ffffff",
      "_stats": {
        "coreVersion": "12.324",
        "systemId": null,
        "systemVersion": null,
        "createdTime": null,
        "modifiedTime": null,
        "lastModifiedBy": null,
        "compendiumSource": null,
        "duplicateSource": null
      },
      "name": "獲得奧秘熟練",
      "img": "modules/dnd5e_classpack/Nicons/Spell_Arcane_Arcane04.png",
      "type": "base",
      "system": {},
      "description": "",
      "statuses": [],
      "sort": 0,
      "_key": "!items.effects!8uE5wtdhiwvoTzHW.WwkHPYMuFotAiW0I"
    }
  ],
  "folder": null,
  "sort": 0,
  "flags": {},
  "_stats": {
    "coreVersion": "12.324",
    "systemId": null,
    "systemVersion": null,
    "createdTime": null,
    "modifiedTime": null,
    "lastModifiedBy": null,
    "compendiumSource": null,
    "duplicateSource": null
  },
  "ownership": {
    "default": 0
  },
  "_key": "!items!8uE5wtdhiwvoTzHW"
}
