{
  "_id": "xCzpkWI4xZyH1kfH",
  "name": "死亡之友 Death 's Friend",
  "type": "feat",
  "img": "modules/dnd5e_classpack/Nicons/sha_spell_shadow_shadesofdarkness.png",
  "system": {
    "description": {
      "value": "<p>你與死亡的聯繫變得如此緊密，以至於你獲得瞭如下益處：</p>\n<ul>\n<li>當你使用@UUID[Compendium.dnd5e_classpack.extra-ability.tVe8Dhk12i9A1mOd]{墓穴驚嚎}的時候，你可以同時對你的攻擊目標和第二目標造成那份暗蝕傷害，</li>\n<li>在一次長休的結束時，假如你沒有任何@UUID[Compendium.dnd5e_classpack.extra-ability.eXk4FM2eHvy3WS67]{魂器}，死者的靈魂會自動被你吸引，在你手中形成一個魂器。</li>\n</ul>",
      "chat": "",
      "unidentified": ""
    },
    "source": "TCE",
    "activation": {
      "type": "",
      "cost": 0,
      "condition": ""
    },
    "duration": {
      "value": null,
      "units": ""
    },
    "cover": null,
    "crewed": false,
    "target": {
      "value": null,
      "width": null,
      "units": "",
      "type": ""
    },
    "range": {
      "value": null,
      "long": null,
      "units": ""
    },
    "uses": {
      "value": 0,
      "max": 0,
      "per": null,
      "recovery": ""
    },
    "consume": {
      "type": "",
      "target": null,
      "amount": null
    },
    "ability": null,
    "actionType": "",
    "attackBonus": 0,
    "chatFlavor": "",
    "critical": null,
    "damage": {
      "parts": [],
      "versatile": ""
    },
    "formula": "",
    "save": {
      "ability": "",
      "dc": null,
      "scaling": "spell"
    },
    "type": {
      "value": "class",
      "subtype": ""
    },
    "requirements": "鬼魅等級 17",
    "recharge": {
      "value": null,
      "charged": false
    }
  },
  "effects": [],
  "folder": null,
  "sort": 0,
  "flags": {},
  "ownership": {
    "default": 0
  },
  "_stats": {
    "systemId": "dnd5e",
    "systemVersion": "2.2.0",
    "coreVersion": "12.324",
    "createdTime": null,
    "modifiedTime": 1685192990406,
    "lastModifiedBy": "Jo05tXxu7yf2dQe3",
    "compendiumSource": null,
    "duplicateSource": null
  },
  "_key": "!items!xCzpkWI4xZyH1kfH"
}
