{
  "_id": "l4lNH8vyG9P8hyPv",
  "name": "超魔法：轉化法術 Metamagic ： Transmuted Spell",
  "type": "feat",
  "img": "icons/magic/unholy/orb-swirling-teal.webp",
  "system": {
    "description": {
      "value": "<p>當你施放一個能夠造成以下列表中型別傷害的法術時，你可以使用1術法點將其改為列表中的另一種傷害型別：強酸、冷凍、火焰、閃電、毒素或雷鳴。</p>",
      "chat": "",
      "unidentified": ""
    },
    "source": "TCE",
    "activation": {
      "type": "special",
      "cost": 0,
      "condition": "1 術法點。"
    },
    "duration": {
      "value": null,
      "units": ""
    },
    "cover": null,
    "target": {
      "value": null,
      "width": null,
      "units": "",
      "type": ""
    },
    "range": {
      "value": null,
      "long": null,
      "units": ""
    },
    "uses": {
      "value": 0,
      "max": "0",
      "per": "",
      "recovery": ""
    },
    "consume": {
      "type": "",
      "target": "",
      "amount": null
    },
    "ability": null,
    "actionType": "",
    "attackBonus": 0,
    "chatFlavor": "",
    "critical": null,
    "damage": {
      "parts": [],
      "versatile": ""
    },
    "formula": "",
    "save": {
      "ability": "",
      "dc": null,
      "scaling": "spell"
    },
    "type": {
      "value": "class",
      "subtype": "metamagic"
    },
    "requirements": "術士等級 3",
    "recharge": {
      "value": null,
      "charged": false
    }
  },
  "effects": [],
  "folder": null,
  "sort": 0,
  "flags": {},
  "ownership": {
    "default": 0
  },
  "_stats": {
    "coreVersion": "12.324",
    "systemId": "dnd5e",
    "systemVersion": "3.2.0",
    "createdTime": null,
    "modifiedTime": null,
    "lastModifiedBy": null,
    "compendiumSource": null,
    "duplicateSource": null
  },
  "_key": "!items!l4lNH8vyG9P8hyPv"
}
